{
  "story": {
    "content": "夏休みだ！ってことで一念発起、ビジネス法務3級に挑戦！最初は「2週間でイケるっしょ！」ってナメてたけど、法律用語の嵐にマジ焦った！でも、YouTube先生のおかげで何とか理解！マジで毎日8時間ぶっ通しで勉強！最後はもう意地！諦めずに食らいついたら、まさかの合格！努力は裏切らないってマジだった！次は2級目指すぞー！",
    "tone": "エネルギッシュな口調",
    "themes": [
      "継続",
      "努力",
      "成長"
    ]
  },
  "generated_date": "2025-07-07",
  "pattern_info": {
    "persona": "1ヶ月で合格を目指した人",
    "occupation": "フリーランス",
    "tone": "エネルギッシュな口調",
    "study_period": "2週間",
    "difficulty": "理解が追いつかなくて",
    "success_factor": "自分のペースを見つけること"
  }
}